MANIFEST.in
setup.cfg
setup.py
src/collective/__init__.py
src/collective.searchtool.egg-info/PKG-INFO
src/collective.searchtool.egg-info/SOURCES.txt
src/collective.searchtool.egg-info/dependency_links.txt
src/collective.searchtool.egg-info/entry_points.txt
src/collective.searchtool.egg-info/namespace_packages.txt
src/collective.searchtool.egg-info/not-zip-safe
src/collective.searchtool.egg-info/requires.txt
src/collective.searchtool.egg-info/top_level.txt
src/collective/searchtool/HISTORY.txt
src/collective/searchtool/README.txt
src/collective/searchtool/__init__.py
src/collective/searchtool/collective.searchtool.css
src/collective/searchtool/configure.zcml
src/collective/searchtool/interfaces.py
src/collective/searchtool/namespace.py
src/collective/searchtool/result.pt
src/collective/searchtool/result.py
src/collective/searchtool/result_image.pt
src/collective/searchtool/simple.py
src/collective/searchtool/simple_plone.pt
src/collective/searchtool/simple_results.pt
src/collective/searchtool/tests.py
src/collective/searchtool/profiles/default/browserlayer.xml
src/collective/searchtool/profiles/default/cssregistry.xml
src/collective/searchtool/profiles/default/metadata.xml
src/collective/searchtool/profiles/default/skins.xml
src/collective/searchtool/skins/collective.searchtool/search.pt