Metadata-Version: 1.0
Name: collective.searchtool
Version: 0.1.5
Summary: Search tool for plone using z3c.form.
Home-page: https://svn.plone.org/svn/collective/collective.searchtool
Author: Rok Garbas
Author-email: rok@garbas.si
License: GPL
Keywords: zope plone search
Platform: UNKNOWN
Classifier: Framework :: Plone
Classifier: Programming Language :: Python
Classifier: Topic :: Software Development :: Libraries :: Python Modules
